itu/__init__.py
itu/algs4/__init__.py
itu/algs4/errors/__init__.py
itu/algs4/errors/errors.py
itu/algs4/fundamentals/__init__.py
itu/algs4/fundamentals/bag.py
itu/algs4/fundamentals/binary_search.py
itu/algs4/fundamentals/evaluate.py
itu/algs4/fundamentals/java_helper.py
itu/algs4/fundamentals/queue.py
itu/algs4/fundamentals/stack.py
itu/algs4/fundamentals/three_sum.py
itu/algs4/fundamentals/three_sum_fast.py
itu/algs4/fundamentals/two_sum_fast.py
itu/algs4/fundamentals/uf.py
itu/algs4/graphs/Arbitrage.py
itu/algs4/graphs/CPM.py
itu/algs4/graphs/__init__.py
itu/algs4/graphs/acyclic_lp.py
itu/algs4/graphs/acyclic_sp.py
itu/algs4/graphs/bellman_ford_sp.py
itu/algs4/graphs/bipartite.py
itu/algs4/graphs/breadth_first_paths.py
itu/algs4/graphs/cc.py
itu/algs4/graphs/cycle.py
itu/algs4/graphs/degrees_of_separation.py
itu/algs4/graphs/depth_first_order.py
itu/algs4/graphs/depth_first_paths.py
itu/algs4/graphs/depth_first_search.py
itu/algs4/graphs/digraph.py
itu/algs4/graphs/dijkstra_all_pairs_sp.py
itu/algs4/graphs/dijkstra_sp.py
itu/algs4/graphs/dijkstra_undirected_sp.py
itu/algs4/graphs/directed_cycle.py
itu/algs4/graphs/directed_dfs.py
itu/algs4/graphs/directed_edge.py
itu/algs4/graphs/edge.py
itu/algs4/graphs/edge_weighted_digraph.py
itu/algs4/graphs/edge_weighted_directed_cycle.py
itu/algs4/graphs/edge_weighted_directed_cycle_anton.py
itu/algs4/graphs/edge_weighted_graph.py
itu/algs4/graphs/graph.py
itu/algs4/graphs/kosaraju_sharir_scc.py
itu/algs4/graphs/kruskal_mst.py
itu/algs4/graphs/lazy_prim_mst.py
itu/algs4/graphs/prim_mst.py
itu/algs4/graphs/symbol_digraph.py
itu/algs4/graphs/symbol_graph.py
itu/algs4/graphs/topological.py
itu/algs4/graphs/transitive_closure.py
itu/algs4/searching/__init__.py
itu/algs4/searching/binary_search_st.py
itu/algs4/searching/bst.py
itu/algs4/searching/file_index.py
itu/algs4/searching/frequency_counter.py
itu/algs4/searching/linear_probing_hst.py
itu/algs4/searching/lookup_csv.py
itu/algs4/searching/lookup_index.py
itu.algs4-0.2.5.dist-info/LICENSE
itu.algs4-0.2.5.dist-info/METADATA
itu.algs4-0.2.5.dist-info/WHEEL
itu.algs4-0.2.5.dist-info/top_level.txt
itu.algs4-0.2.5.dist-info/RECORD
