Metadata-Version: 2.1
Name: itu.algs4
Version: 0.2.5
Summary: Python 3 port of the Java code in "Algorithms, 4th Edition" by Sedgewick and Wayne
Home-page: https://github.com/itu-algorithms/itu.algs4/
Author: Algorithms group at ITU Copenhagen
License: GNU General Public License v3 (GPLv3)
Platform: any
Classifier: License :: OSI Approved :: GNU General Public License v3 (GPLv3)
Classifier: Operating System :: OS Independent
Classifier: Natural Language :: English
Classifier: Programming Language :: Python
Classifier: Programming Language :: Python :: 3
Classifier: Topic :: Utilities
Classifier: Intended Audience :: Developers
Classifier: Intended Audience :: Education
Classifier: Intended Audience :: Science/Research
Classifier: Topic :: Software Development :: Libraries :: Python Modules
Provides-Extra: audio
Requires-Dist: numpy ; extra == 'audio'
Provides-Extra: dev
Requires-Dist: flake8 ; extra == 'dev'
Requires-Dist: black ; extra == 'dev'
Requires-Dist: isort ; extra == 'dev'
Requires-Dist: pytest ; extra == 'dev'
Requires-Dist: pytest-cov ; extra == 'dev'
Requires-Dist: coveralls ; extra == 'dev'
Requires-Dist: mypy ; extra == 'dev'
Provides-Extra: visual
Requires-Dist: pygame ; extra == 'visual'
